{
	"name": "SourceBrickable_Themes",
	"properties": {
		"linkedServiceName": {
			"referenceName": "Brickable",
			"type": "LinkedServiceReference"
		},
		"annotations": [],
		"type": "DelimitedText",
		"typeProperties": {
			"location": {
				"type": "HttpServerLocation",
				"relativeUrl": "media/downloads/themes.csv.gz?1646730480.4507792"
			},
			"columnDelimiter": ",",
			"rowDelimiter": "\n",
			"compressionCodec": "gzip",
			"compressionLevel": "Optimal",
			"escapeChar": "\\",
			"firstRowAsHeader": true,
			"quoteChar": "\""
		},
		"schema": [
			{
				"name": "id",
				"type": "String"
			},
			{
				"name": "name",
				"type": "String"
			},
			{
				"name": "parent_id",
				"type": "String"
			}
		]
	},
	"type": "Microsoft.DataFactory/factories/datasets"
}